{"ticker":"GS","history":[{"year":2015,"revenue":0,"net_income":5568000000,"fcf":-1833000000,"shares":419480736,"roe":6.42007194908219,"net_margin":0,"fcf_margin":0},{"year":2016,"revenue":0,"net_income":7087000000,"fcf":3629000000,"shares":392632230,"roe":8.15600796381757,"net_margin":0,"fcf_margin":0},{"year":2017,"revenue":0,"net_income":3685000000,"fcf":-23673000000,"shares":374808805,"roe":4.4806244908381263,"net_margin":0,"fcf_margin":0},{"year":2018,"revenue":0,"net_income":9860000000,"fcf":8582000000,"shares":367741973,"roe":10.933081998114986,"net_margin":0,"fcf_margin":0},{"year":2019,"revenue":0,"net_income":7897000000,"fcf":15425000000,"shares":347343184,"roe":8.7486844291807468,"net_margin":0,"fcf_margin":0},{"year":2020,"revenue":0,"net_income":8915000000,"fcf":-24844000000,"shares":344088725,"roe":9.29304090397365,"net_margin":0,"fcf_margin":0},{"year":2021,"revenue":0,"net_income":21151000000,"fcf":1631000000,"shares":333573254,"roe":19.241125848297948,"net_margin":0,"fcf_margin":0},{"year":2022,"revenue":0,"net_income":10764000000,"fcf":4960000000,"shares":334918639,"roe":9.1851624299208972,"net_margin":0,"fcf_margin":0},{"year":2023,"revenue":0,"net_income":7907000000,"fcf":-14903000000,"shares":323376354,"roe":6.7636114794063564,"net_margin":0,"fcf_margin":0},{"year":2024,"revenue":0,"net_income":13525000000,"fcf":-15303000000,"shares":310653708,"roe":11.086429063247975,"net_margin":0,"fcf_margin":0},{"year":2025,"revenue":0,"net_income":0,"fcf":0,"shares":0,"roe":0,"net_margin":0,"fcf_margin":0}],"generated_at":"2026-02-19T10:53:04Z","quality_score":0}