{"ticker":"MNST","annual":[{"year":2011,"revenue":0,"gross_profit":214244000,"operating_income":456423000,"net_income":64536000,"eps":0,"total_assets":1362399000,"total_liabilities":0,"total_debt":0,"cash_and_equiv":359331000,"total_equity":979158000,"operating_cash_flow":0,"capex":25552000,"dividends_paid":0,"shares_outstanding":174277000,"free_cash_flow":-25552000,"gross_margin":0,"operating_margin":0,"net_margin":0,"fcf_margin":0,"roe":6.5909689753849738,"roa":4.7369382978114345},{"year":2012,"revenue":0,"gross_profit":243887000,"operating_income":550623000,"net_income":67984000,"eps":0,"total_assets":1043325000,"total_liabilities":0,"total_debt":0,"cash_and_equiv":222514000,"total_equity":644397000,"operating_cash_flow":0,"capex":42935000,"dividends_paid":0,"shares_outstanding":165776000,"free_cash_flow":-42935000,"gross_margin":0,"operating_margin":0,"net_margin":0,"fcf_margin":0,"roe":10.550018078917189,"roa":6.5160903841085},{"year":2013,"revenue":0,"gross_profit":277160000,"operating_income":572916000,"net_income":76105000,"eps":0,"total_assets":1420509000,"total_liabilities":0,"total_debt":0,"cash_and_equiv":211349000,"total_equity":992279000,"operating_cash_flow":0,"capex":40762000,"dividends_paid":0,"shares_outstanding":166822000,"free_cash_flow":-40762000,"gross_margin":0,"operating_margin":0,"net_margin":0,"fcf_margin":0,"roe":7.66971789184292,"roa":5.35758661155966},{"year":2014,"revenue":0,"gross_profit":331784000,"operating_income":747505000,"net_income":125332000,"eps":0,"total_assets":1938875000,"total_liabilities":0,"total_debt":0,"cash_and_equiv":370323000,"total_equity":1515150000,"operating_cash_flow":0,"capex":27952000,"dividends_paid":0,"shares_outstanding":167722000,"free_cash_flow":-27952000,"gross_margin":0,"operating_margin":0,"net_margin":0,"fcf_margin":0,"roe":8.27192027192027,"roa":6.4641609180581527},{"year":2015,"revenue":0,"gross_profit":403360000,"operating_income":893653000,"net_income":138741000,"eps":0,"total_assets":5675189000,"total_liabilities":0,"total_debt":0,"cash_and_equiv":2175417000,"total_equity":4809410000,"operating_cash_flow":0,"capex":35605000,"dividends_paid":0,"shares_outstanding":202900000,"free_cash_flow":-35605000,"gross_margin":0,"operating_margin":0,"net_margin":0,"fcf_margin":0,"roe":2.8847821250423649,"roa":2.4446939123965739},{"year":2016,"revenue":0,"gross_profit":498113000,"operating_income":1085338000,"net_income":172946000,"eps":0,"total_assets":4153471000,"total_liabilities":0,"total_debt":0,"cash_and_equiv":377582000,"total_equity":3329709000,"operating_cash_flow":0,"capex":99819000,"dividends_paid":0,"shares_outstanding":566566000,"free_cash_flow":-99819000,"gross_margin":0,"operating_margin":0,"net_margin":0,"fcf_margin":0,"roe":5.19402746606385,"roa":4.1638908758481756},{"year":2017,"revenue":0,"gross_profit":503610000,"operating_income":1198787000,"net_income":201321000,"eps":0,"total_assets":4791012000,"total_liabilities":0,"total_debt":0,"cash_and_equiv":528622000,"total_equity":3895212000,"operating_cash_flow":987731000,"capex":83435000,"dividends_paid":0,"shares_outstanding":566298000,"free_cash_flow":904296000,"gross_margin":0,"operating_margin":0,"net_margin":0,"fcf_margin":0,"roe":5.1684221551997682,"roa":4.2020558495783353},{"year":2018,"revenue":924229000,"gross_profit":552201000,"operating_income":1283619000,"net_income":239105000,"eps":0,"total_assets":4526891000,"total_liabilities":0,"total_debt":0,"cash_and_equiv":637513000,"total_equity":3610901000,"operating_cash_flow":1161881000,"capex":61941000,"dividends_paid":0,"shares_outstanding":543676000,"free_cash_flow":1099940000,"gross_margin":59.747205508591485,"operating_margin":138.88538446640388,"net_margin":25.870752811262143,"fcf_margin":119.01163023449817,"roe":6.6217545150088579,"roa":5.2818810967615519},{"year":2019,"revenue":1017206000,"gross_profit":610768000,"operating_income":1402939000,"net_income":254954000,"eps":0,"total_assets":5150352000,"total_liabilities":0,"total_debt":0,"cash_and_equiv":797957000,"total_equity":4171281000,"operating_cash_flow":1113762000,"capex":101661000,"dividends_paid":0,"shares_outstanding":536698000,"free_cash_flow":1012101000,"gross_margin":60.04368829912525,"operating_margin":137.92083412799374,"net_margin":25.064146298783136,"fcf_margin":99.498135087681348,"roe":6.11212718586928,"roa":4.9502247613367},{"year":2020,"revenue":1196283000,"gross_profit":690684000,"operating_income":1633153000,"net_income":471736000,"eps":0,"total_assets":6202716000,"total_liabilities":0,"total_debt":0,"cash_and_equiv":1180413000,"total_equity":5160860000,"operating_cash_flow":1364163000,"capex":48722000,"dividends_paid":0,"shares_outstanding":528097000,"free_cash_flow":1315441000,"gross_margin":57.7358367543466,"operating_margin":136.51895078338487,"net_margin":39.433478533089577,"fcf_margin":109.96068655995279,"roe":9.1406471014520836,"roa":7.60531354329297},{"year":2021,"revenue":5541352000,"gross_profit":3108513000,"operating_income":1797467000,"net_income":1377475000,"eps":0,"total_assets":7804784000,"total_liabilities":0,"total_debt":0,"cash_and_equiv":1326462000,"total_equity":6566951000,"operating_cash_flow":1155741000,"capex":43868000,"dividends_paid":0,"shares_outstanding":529323000,"free_cash_flow":1111873000,"gross_margin":56.096652946789881,"operating_margin":32.437336592225144,"net_margin":24.858103221018986,"fcf_margin":20.065013014874346,"roe":20.975868405291891,"roa":17.649111109288867},{"year":2022,"revenue":6311050000,"gross_profit":3174567000,"operating_income":1584721000,"net_income":1191624000,"eps":0,"total_assets":8293105000,"total_liabilities":0,"total_debt":0,"cash_and_equiv":1307141000,"total_equity":7025041000,"operating_cash_flow":887699000,"capex":188726000,"dividends_paid":0,"shares_outstanding":522300000,"free_cash_flow":698973000,"gross_margin":50.301724752616437,"operating_margin":25.11025899018388,"net_margin":18.881549029083907,"fcf_margin":11.07538365248255,"roe":16.962520218743208,"roa":14.368852197096263},{"year":2023,"revenue":7140027000,"gross_profit":3794206000,"operating_income":1953355000,"net_income":1630988000,"eps":0,"total_assets":9686522000,"total_liabilities":0,"total_debt":0,"cash_and_equiv":2297675000,"total_equity":8228744000,"operating_cash_flow":1717753000,"capex":221428000,"dividends_paid":0,"shares_outstanding":1041571000,"free_cash_flow":1496325000,"gross_margin":53.139939106672848,"operating_margin":27.357809711363835,"net_margin":22.8428828070258,"fcf_margin":20.956853524503479,"roe":19.820619039795137,"roa":16.837705009083756},{"year":2024,"revenue":7492709000,"gross_profit":4048878000,"operating_income":1930294000,"net_income":1509048000,"eps":0,"total_assets":7719089000,"total_liabilities":0,"total_debt":373951000,"cash_and_equiv":1533287000,"total_equity":5957718000,"operating_cash_flow":1928533000,"capex":264074000,"dividends_paid":0,"shares_outstanding":973079000,"free_cash_flow":1664459000,"gross_margin":54.037571724726,"operating_margin":25.762297721691844,"net_margin":20.140218978209351,"fcf_margin":22.214382007895942,"roe":25.329295545710622,"roa":19.549560835482012},{"year":2025,"revenue":8294343000,"gross_profit":4632195000,"operating_income":2419354000,"net_income":1905432000,"eps":0,"total_assets":9988945000,"total_liabilities":0,"total_debt":373951000,"cash_and_equiv":2088117000,"total_equity":8254108000,"operating_cash_flow":2098177000,"capex":132275000,"dividends_paid":0,"shares_outstanding":978113000,"free_cash_flow":1965902000,"gross_margin":55.847642182147517,"operating_margin":29.1687237916252,"net_margin":22.972669444704664,"fcf_margin":23.701720558216607,"roe":23.084650697567806,"roa":19.075407863392982}],"quarterly":[{"year":2021,"quarter":1,"revenue":1243816000,"gross_profit":714935000,"operating_income":414146000,"net_income":315194000,"eps":0,"total_assets":6534366000,"total_liabilities":0,"total_debt":0,"cash_and_equiv":1178879000,"total_equity":5459437000,"operating_cash_flow":175473000,"capex":8400000,"dividends_paid":0,"shares_outstanding":528439000,"free_cash_flow":167073000,"gross_margin":57.479160904828362,"operating_margin":33.296403969719,"net_margin":25.340886433363135,"fcf_margin":13.432292236150683,"roe":5.7733791964262977,"roa":4.8236355294453972},{"year":2021,"quarter":2,"revenue":1461934000,"gross_profit":836838000,"operating_income":525975000,"net_income":403762000,"eps":0,"total_assets":7071543000,"total_liabilities":0,"total_debt":0,"cash_and_equiv":1584239000,"total_equity":5905498000,"operating_cash_flow":586586000,"capex":15522000,"dividends_paid":0,"shares_outstanding":528857000,"free_cash_flow":571064000,"gross_margin":57.2418453911052,"operating_margin":35.9780263678114,"net_margin":27.618346655868187,"fcf_margin":39.062228527416423,"roe":6.8370525229201675,"roa":5.7096732636710268},{"year":2021,"quarter":3,"revenue":1410557000,"gross_profit":789158000,"operating_income":444464000,"net_income":337205000,"eps":0,"total_assets":7449408000,"total_liabilities":0,"total_debt":0,"cash_and_equiv":1712671000,"total_equity":6244997000,"operating_cash_flow":927982000,"capex":28131000,"dividends_paid":0,"shares_outstanding":529132000,"free_cash_flow":899851000,"gross_margin":55.9465516104631,"operating_margin":31.509822006483962,"net_margin":23.905804586415151,"fcf_margin":63.794018958468179,"roe":5.3996022736279938,"roa":4.5266013084529666},{"year":2021,"quarter":4,"revenue":0,"gross_profit":0,"operating_income":0,"net_income":0,"eps":0,"total_assets":0,"total_liabilities":0,"total_debt":0,"cash_and_equiv":0,"total_equity":0,"operating_cash_flow":0,"capex":0,"dividends_paid":0,"shares_outstanding":0,"free_cash_flow":0,"gross_margin":0,"operating_margin":0,"net_margin":0,"fcf_margin":0,"roe":0,"roa":0},{"year":2022,"quarter":1,"revenue":1518574000,"gross_profit":776667000,"operating_income":399489000,"net_income":294203000,"eps":0,"total_assets":8187459000,"total_liabilities":0,"total_debt":0,"cash_and_equiv":1014786000,"total_equity":6866672000,"operating_cash_flow":-351000,"capex":21511000,"dividends_paid":0,"shares_outstanding":529642000,"free_cash_flow":-21862000,"gross_margin":51.144494769435013,"operating_margin":26.306851032613494,"net_margin":19.373636055931421,"fcf_margin":-1.4396400833940262,"roe":4.2845063809659178,"roa":3.59333707808491},{"year":2022,"quarter":2,"revenue":1655260000,"gross_profit":779861000,"operating_income":372951000,"net_income":273360000,"eps":0,"total_assets":8175012000,"total_liabilities":0,"total_debt":0,"cash_and_equiv":1132039000,"total_equity":6809178000,"operating_cash_flow":130663000,"capex":99446000,"dividends_paid":0,"shares_outstanding":526772000,"free_cash_flow":31217000,"gross_margin":47.114108961734111,"operating_margin":22.531263970614887,"net_margin":16.514626101035486,"fcf_margin":1.8859272863477641,"roe":4.014581495740015,"roa":3.3438483026079964},{"year":2022,"quarter":3,"revenue":1624286000,"gross_profit":833725000,"operating_income":417930000,"net_income":322387000,"eps":0,"total_assets":8204805000,"total_liabilities":0,"total_debt":0,"cash_and_equiv":1303048000,"total_equity":6815760000,"operating_cash_flow":589186000,"capex":136158000,"dividends_paid":0,"shares_outstanding":523965000,"free_cash_flow":453028000,"gross_margin":51.32870689028902,"operating_margin":25.730074629714224,"net_margin":19.847920871078124,"fcf_margin":27.8909009866489,"roe":4.7300227707548386,"roa":3.9292463379690314},{"year":2022,"quarter":4,"revenue":0,"gross_profit":0,"operating_income":0,"net_income":0,"eps":0,"total_assets":0,"total_liabilities":0,"total_debt":0,"cash_and_equiv":0,"total_equity":0,"operating_cash_flow":0,"capex":0,"dividends_paid":0,"shares_outstanding":0,"free_cash_flow":0,"gross_margin":0,"operating_margin":0,"net_margin":0,"fcf_margin":0,"roe":0,"roa":0},{"year":2023,"quarter":1,"revenue":1698930000,"gross_profit":897849000,"operating_income":485064000,"net_income":397444000,"eps":0,"total_assets":8844362000,"total_liabilities":0,"total_debt":0,"cash_and_equiv":1672660000,"total_equity":7395360000,"operating_cash_flow":424475000,"capex":40100000,"dividends_paid":0,"shares_outstanding":1046616000,"free_cash_flow":384375000,"gross_margin":52.847910155215338,"operating_margin":28.551146898341894,"net_margin":23.3937831458624,"fcf_margin":22.624534265684872,"roe":5.3742346552432876,"roa":4.493755456866193},{"year":2023,"quarter":2,"revenue":1854961000,"gross_profit":974222000,"operating_income":523805000,"net_income":413871000,"eps":0,"total_assets":9263338000,"total_liabilities":0,"total_debt":0,"cash_and_equiv":1869774000,"total_equity":7841464000,"operating_cash_flow":763162000,"capex":82425000,"dividends_paid":0,"shares_outstanding":1047485000,"free_cash_flow":680737000,"gross_margin":52.519810389544574,"operating_margin":28.238059991557773,"net_margin":22.311574205603243,"fcf_margin":36.698183951037244,"roe":5.27798125452084,"roa":4.4678386991816561},{"year":2023,"quarter":3,"revenue":1856028000,"gross_profit":983763000,"operating_income":510527000,"net_income":1264009000,"eps":0,"total_assets":9314338000,"total_liabilities":0,"total_debt":0,"cash_and_equiv":1773849000,"total_equity":7873149000,"operating_cash_flow":1283426000,"capex":110224000,"dividends_paid":0,"shares_outstanding":1040420000,"free_cash_flow":1173202000,"gross_margin":53.003672358391142,"operating_margin":27.506427704754454,"net_margin":68.1029057751284,"fcf_margin":63.2103610505876,"roe":16.054681551181112,"roa":13.5705725946385},{"year":2023,"quarter":4,"revenue":0,"gross_profit":0,"operating_income":0,"net_income":0,"eps":0,"total_assets":0,"total_liabilities":0,"total_debt":0,"cash_and_equiv":0,"total_equity":0,"operating_cash_flow":0,"capex":0,"dividends_paid":0,"shares_outstanding":0,"free_cash_flow":0,"gross_margin":0,"operating_margin":0,"net_margin":0,"fcf_margin":0,"roe":0,"roa":0},{"year":2024,"quarter":1,"revenue":1899098000,"gross_profit":1027129000,"operating_income":541991000,"net_income":442049000,"eps":0,"total_assets":10098066000,"total_liabilities":0,"total_debt":0,"cash_and_equiv":2576524000,"total_equity":8577789000,"operating_cash_flow":412142000,"capex":66044000,"dividends_paid":0,"shares_outstanding":1041698000,"free_cash_flow":346098000,"gross_margin":54.08509724090068,"operating_margin":28.539390805529784,"net_margin":23.276787190550461,"fcf_margin":18.22433597423619,"roe":5.1534142422948381,"roa":4.3775610101973985},{"year":2024,"quarter":2,"revenue":1900597000,"gross_profit":1019506000,"operating_income":527163000,"net_income":425369000,"eps":0,"total_assets":8060904000,"total_liabilities":0,"total_debt":748740000,"cash_and_equiv":1564734000,"total_equity":5866323000,"operating_cash_flow":848433000,"capex":125812000,"dividends_paid":0,"shares_outstanding":983380000,"free_cash_flow":722621000,"gross_margin":53.6413558476626,"operating_margin":27.736705887676344,"net_margin":22.380809819230485,"fcf_margin":38.0207376945244,"roe":7.251032716746078,"roa":5.2769391621584871},{"year":2024,"quarter":3,"revenue":1880973000,"gross_profit":999799000,"operating_income":479916000,"net_income":370919000,"eps":0,"total_assets":8053301000,"total_liabilities":0,"total_debt":748842000,"cash_and_equiv":1625339000,"total_equity":5779400000,"operating_cash_flow":1466832000,"capex":172795000,"dividends_paid":0,"shares_outstanding":972450000,"free_cash_flow":1294037000,"gross_margin":53.153288218384844,"operating_margin":25.514241831222456,"net_margin":19.719528137830793,"fcf_margin":68.7961496523342,"roe":6.41794996020348,"roa":4.6058007766008},{"year":2024,"quarter":4,"revenue":0,"gross_profit":0,"operating_income":0,"net_income":0,"eps":0,"total_assets":0,"total_liabilities":0,"total_debt":0,"cash_and_equiv":0,"total_equity":0,"operating_cash_flow":0,"capex":0,"dividends_paid":0,"shares_outstanding":0,"free_cash_flow":0,"gross_margin":0,"operating_margin":0,"net_margin":0,"fcf_margin":0,"roe":0,"roa":0},{"year":2025,"quarter":1,"revenue":1854558000,"gross_profit":1047962000,"operating_income":569745000,"net_income":442993000,"eps":0,"total_assets":8227028000,"total_liabilities":0,"total_debt":199059000,"cash_and_equiv":1903419000,"total_equity":6519439000,"operating_cash_flow":507600000,"capex":29056000,"dividends_paid":0,"shares_outstanding":975143000,"free_cash_flow":478544000,"gross_margin":56.507372646204644,"operating_margin":30.7213362968427,"net_margin":23.886715864373073,"fcf_margin":25.803668583026251,"roe":6.7949558236529244,"roa":5.38460547356834},{"year":2025,"quarter":2,"revenue":2111593000,"gross_profit":1176413000,"operating_income":631622000,"net_income":488794000,"eps":0,"total_assets":8729888000,"total_liabilities":0,"total_debt":373951000,"cash_and_equiv":1926927000,"total_equity":7191304000,"operating_cash_flow":973616000,"capex":60460000,"dividends_paid":0,"shares_outstanding":976398000,"free_cash_flow":913156000,"gross_margin":55.7121092937891,"operating_margin":29.91210900964343,"net_margin":23.148116137911046,"fcf_margin":43.244886680340386,"roe":6.7970148390333662,"roa":5.59908672367847},{"year":2025,"quarter":3,"revenue":2197139000,"gross_profit":1224486000,"operating_income":675352000,"net_income":524455000,"eps":0,"total_assets":9611273000,"total_liabilities":0,"total_debt":373951000,"cash_and_equiv":2292939000,"total_equity":7745160000,"operating_cash_flow":1718762000,"capex":104101000,"dividends_paid":0,"shares_outstanding":976997000,"free_cash_flow":1614661000,"gross_margin":55.73093008680835,"operating_margin":30.737791282208367,"net_margin":23.8699053632929,"fcf_margin":73.48925124901065,"roe":6.771390132676407,"roa":5.4566653137414782},{"year":2025,"quarter":4,"revenue":0,"gross_profit":0,"operating_income":0,"net_income":0,"eps":0,"total_assets":0,"total_liabilities":0,"total_debt":0,"cash_and_equiv":0,"total_equity":0,"operating_cash_flow":0,"capex":0,"dividends_paid":0,"shares_outstanding":0,"free_cash_flow":0,"gross_margin":0,"operating_margin":0,"net_margin":0,"fcf_margin":0,"roe":0,"roa":0}],"generated_at":"2026-04-05T10:42:23Z"}