{"ticker":"VLO","history":[{"year":2015,"revenue":0,"net_income":298000000,"fcf":3261000000,"shares":497000000,"roe":1.39552308700946,"net_margin":0,"fcf_margin":0},{"year":2016,"revenue":0,"net_income":2282000000,"fcf":2824000000,"shares":461000000,"roe":10.942744797161216,"net_margin":0,"fcf_margin":0},{"year":2017,"revenue":0,"net_income":4051000000,"fcf":3534000000,"shares":442000000,"roe":17.689956331877728,"net_margin":0,"fcf_margin":0},{"year":2018,"revenue":0,"net_income":3113000000,"fcf":995000000,"shares":426000000,"roe":13.694954027539483,"net_margin":0,"fcf_margin":0},{"year":2019,"revenue":0,"net_income":2415000000,"fcf":2685000000,"shares":413000000,"roe":10.716187433439829,"net_margin":0,"fcf_margin":0},{"year":2020,"revenue":0,"net_income":-1426000000,"fcf":-1488000000,"shares":407000000,"roe":-7.2599531615925059,"net_margin":0,"fcf_margin":0},{"year":2021,"revenue":0,"net_income":924000000,"fcf":3401000000,"shares":407000000,"roe":4.6626633698339814,"net_margin":0,"fcf_margin":0},{"year":2022,"revenue":0,"net_income":11485000000,"fcf":9837000000,"shares":395000000,"roe":45.09580650227737,"net_margin":0,"fcf_margin":0},{"year":2023,"revenue":0,"net_income":8808000000,"fcf":7313000000,"shares":353000000,"roe":30.879259570887672,"net_margin":0,"fcf_margin":0},{"year":2024,"revenue":0,"net_income":2762000000,"fcf":4626000000,"shares":322000000,"roe":10.035972530067948,"net_margin":0,"fcf_margin":0},{"year":2025,"revenue":0,"net_income":0,"fcf":0,"shares":0,"roe":0,"net_margin":0,"fcf_margin":0}],"generated_at":"2026-02-13T02:42:25Z","quality_score":0}